{
  "neoforge:conditions": [
    {
      "type": "neoforge:mod_loaded",
      "modid": "create"
    }
  ],
  "type": "create:mixing",
  "ingredients": [
    {
      "tag": "c:flour"
    },
    {
      "tag": "extradelight:sweetener"
    },
    {
      "tag": "c:butter"
    },
    {
      "tag": "c:eggs"
    },
    {
      "type": "fluid_stack",
      "amount": 250,
      "fluid": "extradelight:nut_butter_fluid"
    }
  ],
  "results": [
    {
      "id": "extradelight:nut_butter_cookie_dough"
    }
  ]
}